CHANGES.rst
CONTRIBUTORS.rst
LICENSE.txt
MANIFEST.in
README.rst
setup.py
django_mediamosa/__init__.py
django_mediamosa/base.py
django_mediamosa/models.py
django_mediamosa/serializers.py
django_mediamosa/urls.py
django_mediamosa/views.py
django_mediamosa.egg-info/PKG-INFO
django_mediamosa.egg-info/SOURCES.txt
django_mediamosa.egg-info/dependency_links.txt
django_mediamosa.egg-info/pbr.json
django_mediamosa.egg-info/requires.txt
django_mediamosa.egg-info/top_level.txt
tests/__init__.py